businesstime/__init__.py
businesstime/holidays/__init__.py
businesstime/holidays/aus.py
businesstime/holidays/usa.py
businesstime/test/__init__.py
businesstime/test/holidays/__init__.py
businesstime/test/holidays/aus_test.py
businesstime/test/holidays/usa_test.py
businesstime-0.2.1.dist-info/DESCRIPTION.rst
businesstime-0.2.1.dist-info/METADATA
businesstime-0.2.1.dist-info/metadata.json
businesstime-0.2.1.dist-info/RECORD
businesstime-0.2.1.dist-info/top_level.txt
businesstime-0.2.1.dist-info/WHEEL
