Metadata-Version: 2.0
Name: businesstime
Version: 0.2.1
Summary: A simple utility for calculating business time aware timedeltas between two datetimes
Home-page: http://github.com/seatgeek/businesstime
Author: SeatGeek
Author-email: hi@seatgeek.com
License: Copyright (c) 2014, SeatGeek, Inc.
